ufork/__init__.py
ufork/ufork.py
ufork-20.11.1.dist-info/LICENSE.txt
ufork-20.11.1.dist-info/METADATA
ufork-20.11.1.dist-info/WHEEL
ufork-20.11.1.dist-info/top_level.txt
ufork-20.11.1.dist-info/RECORD
